{
  "generatedAt": "2026-07-04T11:00:15.221Z",
  "range": {
    "startDate": "2026-06-04",
    "endDate": "2026-07-03"
  },
  "assets": {
    "asset-1": {
      "domain": "clampgen.com",
      "gaPropertyId": "540522281",
      "sessions": 892,
      "clicks": 3,
      "impressions": 143,
      "status": "ok",
      "error": ""
    },
    "asset-2": {
      "domain": "freelanceratewise.com",
      "gaPropertyId": "540671739",
      "sessions": 103,
      "clicks": 0,
      "impressions": 35,
      "status": "ok",
      "error": ""
    },
    "asset-3": {
      "domain": "calmacrocal.com",
      "gaPropertyId": "540909051",
      "sessions": 102,
      "clicks": 0,
      "impressions": 8,
      "status": "ok",
      "error": ""
    },
    "asset-4": {
      "domain": "onerepmaxx.com",
      "gaPropertyId": "540671739",
      "sessions": 103,
      "clicks": 0,
      "impressions": 130,
      "status": "ok",
      "error": ""
    },
    "asset-5": {
      "domain": "srcsetbuilder.com",
      "gaPropertyId": "542208158",
      "sessions": 77,
      "clicks": 0,
      "impressions": 5,
      "status": "ok",
      "error": ""
    }
  }
}
