{
  "generatedAt": "2026-07-06T12:57:55.596Z",
  "range": {
    "startDate": "2026-06-06",
    "endDate": "2026-07-05"
  },
  "assets": {
    "asset-1": {
      "domain": "clampgen.com",
      "gaPropertyId": "540522281",
      "sessions": 914,
      "clicks": 3,
      "impressions": 153,
      "status": "ok",
      "error": ""
    },
    "asset-2": {
      "domain": "freelanceratewise.com",
      "gaPropertyId": "540671739",
      "sessions": 110,
      "clicks": 0,
      "impressions": 37,
      "status": "ok",
      "error": ""
    },
    "asset-3": {
      "domain": "calmacrocal.com",
      "gaPropertyId": "540909051",
      "sessions": 108,
      "clicks": 0,
      "impressions": 9,
      "status": "ok",
      "error": ""
    },
    "asset-4": {
      "domain": "onerepmaxx.com",
      "gaPropertyId": "540671739",
      "sessions": 110,
      "clicks": 0,
      "impressions": 154,
      "status": "ok",
      "error": ""
    },
    "asset-5": {
      "domain": "srcsetbuilder.com",
      "gaPropertyId": "542208158",
      "sessions": 80,
      "clicks": 0,
      "impressions": 5,
      "status": "ok",
      "error": ""
    }
  }
}
